Workbook

Sheet Raw Data
A1: Raw Financial Data (from 10-K Filings)
A3: Metric | B3: 2021 | C3: 2022 | D3: 2023 | E3: 2024 | F3: 2025
A4: Global MAU (M) | B4: 431 | C4: 450 | D4: 498 | E4: 553 | F4: 619
A5: US & Canada MAU (M) | B5: 86 | C5: 88 | D5: 91 | E5: 99 | F5: 103
A6: Europe MAU (M) | B6: 124 | C6: 129 | D6: 136 | E6: 140 | F6: 151
A7: Rest of World MAU (M) | B7: 221 | C7: 233 | D7: 271 | E7: 314 | F7: 365
A9: US & Canada ARPU ($) | B9: 19.38 | C9: 23.99 | D9: 25.57 | E9: 29.15 | F9: 30.84
A10: Europe ARPU ($) | B10: 2.82 | C10: 3.15 | D10: 3.72 | E10: 4.24 | F10: 5.12
A11: Rest of World ARPU ($) | B11: 0.21 | C11: 0.28 | D11: 0.5 | E11: 0.59 | F11: 0.83
A12: Global ARPU ($) | B12: 4.83 | C12: 5.46 | D12: 6.43 | E12: 6.94 | F12: 7.21
A14: Total Revenue ($M) | B14: 2578 | C14: 2803 | D14: 3055 | E14: 3646 | F14: 4222
A15: US & Canada Revenue ($M) | B15: 1665 | C15: 2112 | D15: 2327 | E15: 2884 | F15: 3173
A16: Europe Revenue ($M) | B16: 350 | C16: 406 | D16: 506 | E16: 593 | F16: 775
A17: Rest of World Revenue ($M) | B17: 46 | C17: 65 | D17: 136 | E17: 169 | F17: 274
... A30: Headcount | B30: 3209 | C30: 3883 | D30: 3991 | E30: 4666 | F30: 5265
A32: Source: Pinterest 10-K filings (FY2024, FY2025). SEC EDGAR.
A33: Note: 2021-2022 MAU geographic splits and ARPU are estimated from reported growth rates.

Sheet Trend Analysis
A1: Trend Analysis: Growth Metrics & CAGR
A3: MAU Growth Analysis
A4: Metric | B4: 2021 | C4: 2022 | D4: 2023 | E4: 2024 | F4: 2025 | G4: CAGR (4yr)
A5: Global MAU (M) | B5: ='Raw Data'!B4 -> 431 | C5: ='Raw Data'!C4 -> 450 | D5: ='Raw Data'!D4 -> 498 | E5: ='Raw Data'!E4 -> 553 | F5: ='Raw Data'!F4 -> 619 | G5: =(F5/B5)^(1/4)-1 -> 0.094720737
A6: US & Canada MAU (M) | B6: ='Raw Data'!B5 -> 86 | C6: ='Raw Data'!C5 -> 88 | D6: ='Raw Data'!D5 -> 91 | E6: ='Raw Data'!E5 -> 99 | F6: ='Raw Data'!F5 -> 103 | G6: =(F6/B6)^(1/4)-1 -> 0.04612768
A7: Europe MAU (M) | B7: ='Raw Data'!B6 -> 124 | C7: ='Raw Data'!C6 -> 129 | D7: ='Raw Data'!D6 -> 136 | E7: ='Raw Data'!E6 -> 140 | F7: ='Raw Data'!F6 -> 151 | G7: =(F7/B7)^(1/4)-1 -> 0.050482485
A8: ROW MAU (M) | B8: ='Raw Data'!B7 -> 221 | C8: ='Raw Data'!C7 -> 233 | D8: ='Raw Data'!D7 -> 271 | E8: ='Raw Data'!E7 -> 314 | F8: ='Raw Data'!F7 -> 365 | G8: =(F8/B8)^(1/4)-1 -> 0.13363996
A10: Global MAU Growth YoY | B10: — | C10: =(C5-B5)/B5 -> 0.044083527 | D10: =(D5-C5)/C5 -> 0.10666667 | E10: =(E5-D5)/D5 -> 0.11044177 | F10: =(F5-E5)/E5 -> 0.11934901
A11: US & Canada MAU Growth YoY | B11: — | C11: =(C6-B6)/B6 -> 0.023255814 | D11: =(D6-C6)/C6 -> 0.034090909 | E11: =(E6-D6)/D6 -> 0.087912088 | F11: =(F6-E6)/E6 -> 0.04040404
A12: Europe MAU Growth YoY | B12: — | C12: =(C7-B7)/B7 -> 0.040322581 | D12: =(D7-C7)/C7 -> 0.054263566 | E12: =(E7-D7)/D7 -> 0.029411765 | F12: =(F7-E7)/E7 -> 0.078571429
A13: ROW MAU Growth YoY | B13: — | C13: =(C8-B8)/B8 -> 0.054298643 | D13: =(D8-C8)/C8 -> 0.16309013 | E13: =(E8-D8)/D8 -> 0.15867159 | F13: =(F8-E8)/E8 -> 0.16242038
A15: ARPU Growth Analysis
A16: Metric | B16: 2021 | C16: 2022 | D16: 2023 | E16: 2024 | F16: 2025 | G16: CAGR (4yr)
A17: Global ARPU ($) | B17: ='Raw Data'!B12 -> 4.83 | C17: ='Raw Data'!C12 -> 5.46 | D17: ='Raw Data'!D12 -> 6.43 | E17: ='Raw Data'!E12 -> 6.94 | F17: ='Raw Data'!F12 -> 7.21 | G17: =(F17/B17)^(1/4)-1 -> 0.10534292
A18: US & Canada ARPU ($) | B18: ='Raw Data'!B9 -> 19.38 | C18: ='Raw Data'!C9 -> 23.99 | D18: ='Raw Data'!D9 -> 25.57 | E18: ='Raw Data'!E9 -> 29.15 | F18: ='Raw Data'!F9 -> 30.84 | G18: =(F18/B18)^(1/4)-1 -> 0.12315618
A19: Europe ARPU ($) | B19: ='Raw Data'!B10 -> 2.82 | C19: ='Raw Data'!C10 -> 3.15 | D19: ='Raw Data'!D10 -> 3.72 | E19: ='Raw Data'!E10 -> 4.24 | F19: ='Raw Data'!F10 -> 5.12 | G19: =(F19/B19)^(1/4)-1 -> 0.16079416
A20: ROW ARPU ($) | B20: ='Raw Data'!B11 -> 0.21 | C20: ='Raw Data'!C11 -> 0.28 | D20: ='Raw Data'!D11 -> 0.5 | E20: ='Raw Data'!E11 -> 0.59 | F20: ='Raw Data'!F11 -> 0.83 | G20: =(F20/B20)^(1/4)-1 -> 0.40998567
A22: Global ARPU Growth YoY | B22: — | C22: =(C17-B17)/B17 -> 0.13043478 | D22: =(D17-C17)/C17 -> 0.17765568 | E22: =(E17-D17)/D17 -> 0.079315708 | F22: =(F17-E17)/E17 -> 0.038904899
A23: US & Canada ARPU Growth YoY | B23: — | C23: =(C18-B18)/B18 -> 0.2378741 | D23: =(D18-C18)/C18 -> 0.065860775 | E23: =(E18-D18)/D18 -> 0.14000782 | F23: =(F18-E18)/E18 -> 0.057975986
A24: Europe ARPU Growth YoY | B24: — | C24: =(C19-B19)/B19 -> 0.11702128 | D24: =(D19-C19)/C19 -> 0.18095238 | E24: =(E19-D19)/D19 -> 0.13978495 | F24: =(F19-E19)/E19 -> 0.20754717
A25: ROW ARPU Growth YoY | B25: — | C25: =(C20-B20)/B20 -> 0.33333333 | D25: =(D20-C20)/C20 -> 0.78571429 | E25: =(E20-D20)/D20 -> 0.18 | F25: =(F20-E20)/E20 -> 0.40677966
A27: Revenue Analysis
A28: Metric | B28: 2021 | C28: 2022 | D28: 2023 | E28: 2024 | F28: 2025 | G28: CAGR (4yr)
A29: Total Revenue ($M) | B29: ='Raw Data'!B14 -> 2578 | C29: ='Raw Data'!C14 -> 2803 | D29: ='Raw Data'!D14 -> 3055 | E29: ='Raw Data'!E14 -> 3646 | F29: ='Raw Data'!F14 -> 4222 | G29: =(F29/B29)^(1/4)-1 -> 0.13125062
A30: US & Canada Revenue ($M) | B30: ='Raw Data'!B15 -> 1665 | C30: ='Raw Data'!C15 -> 2112 | D30: ='Raw Data'!D15 -> 2327 | E30: ='Raw Data'!E15 -> 2884 | F30: ='Raw Data'!F15 -> 3173 | G30: =(F30/B30)^(1/4)-1 -> 0.17493532
A31: Europe Revenue ($M) | B31: ='Raw Data'!B16 -> 350 | C31: ='Raw Data'!C16 -> 406 | D31: ='Raw Data'!D16 -> 506 | E31: ='Raw Data'!E16 -> 593 | F31: ='Raw Data'!F16 -> 775 | G31: =(F31/B31)^(1/4)-1 -> 0.21985557
A32: ROW Revenue ($M) | B32: ='Raw Data'!B17 -> 46 | C32: ='Raw Data'!C17 -> 65 | D32: ='Raw Data'!D17 -> 136 | E32: ='Raw Data'!E17 -> 169 | F32: ='Raw Data'!F17 -> 274 | G32: =(F32/B32)^(1/4)-1 -> 0.56224154
A34: Revenue Growth YoY | B34: — | C34: =(C29-B29)/B29 -> 0.087276959 | D34: =(D29-C29)/C29 -> 0.089903675 | E34: =(E29-D29)/D29 -> 0.19345336 | F34: =(F29-E29)/E29 -> 0.15798135
A35: US & Canada Rev Growth | B35: — | C35: =(C30-B30)/B30 -> 0.26846847 | D35: =(D30-C30)/C30 -> 0.10179924 | E35: =(E30-D30)/D30 -> 0.23936399 | F35: =(F30-E30)/E30 -> 0.10020804
A36: Europe Rev Growth | B36: — | C36: =(C31-B31)/B31 -> 0.16 | D36: =(D31-C31)/C31 -> 0.24630542 | E36: =(E31-D31)/D31 -> 0.17193676 | F36: =(F31-E31)/E31 -> 0.306914
A37: ROW Rev Growth | B37: — | C37: =(C32-B32)/B32 -> 0.41304348 | D37: =(D32-C32)/C32 -> 1.0923077 | E37: =(E32-D32)/D32 -> 0.24264706 | F37: =(F32-E32)/E32 -> 0.62130178
A39: Revenue Share: US & Canada | B39: =B30/B29 -> 0.6458495 | C39: =C30/C29 -> 0.75347842 | D39: =D30/D29 -> 0.76170213 | E39: =E30/E29 -> 0.79100384 | F39: =F30/F29 -> 0.75153955
A40: Revenue Share: Europe | B40: =B31/B29 -> 0.13576416 | C40: =C31/C29 -> 0.14484481 | D40: =D31/D29 -> 0.16563011 | E40: =E31/E29 -> 0.16264399 | F40: =F31/F29 -> 0.18356229
A41: Revenue Share: ROW | B41: =B32/B29 -> 0.017843289 | C41: =C32/C29 -> 0.02318944 | D41: =D32/D29 -> 0.044517185 | E41: =E32/E29 -> 0.046352167 | F41: =F32/F29 -> 0.064898153

Sheet Revenue Driver Model
A1: Revenue Driver Decomposition: Revenue = Users × Engagement × Ads × Price
A3: Advertising Funnel Metrics
A4: Metric | B4: 2022 | C4: 2023 | D4: 2024 | E4: 2025
A5: Average MAUs (M) | B5: 441 | C5: 474 | D5: 525 | E5: 586
A6: WAU/MAU Ratio | B6: 0.62 | C6: 0.62 | D6: 0.62 | E6: 0.62
A7: Avg Weekly Active Users (M) | B7: =B5*B6 -> 273.42 | C7: =C5*C6 -> 293.88 | D7: =D5*D6 -> 325.5 | E7: =E5*E6 -> 363.32
A8: Sessions per WAU per Month (est) | B8: 8.5 | C8: 9 | D8: 9.5 | E8: 10
A9: Total Monthly Sessions (B) | B9: =B7*B8/1000 -> 2.32407 | C9: =C7*C8/1000 -> 2.64492 | D9: =D7*D8/1000 -> 3.09225 | E9: =E7*E8/1000 -> 3.6332
A10: Ads per Session (est) | B10: 3.5 | C10: 3.8 | D10: 4.2 | E10: 5
A11: Total Ads Served (B/yr) | B11: =B9*B10*12 -> 97.61094 | C11: =C9*C10*12 -> 120.60835 | D11: =D9*D10*12 -> 155.8494 | E11: =E9*E10*12 -> 217.992
A13: Effective CPM ($) | B13: =B17/B11 -> 28.716044 | C13: =C17/C11 -> 25.329921 | D13: =D17/D11 -> 23.394379 | E13: =E17/E11 -> 19.367683
A14: CPM Growth YoY | B14: — | C14: =(C13-B13)/B13 -> -0.11791745 | D14: =(D13-C13)/C13 -> -0.07641324 | E14: =(E13-D13)/D13 -> -0.17212238
A16: Implied Revenue ($M) | B16: =B11*B13 -> 2803 | C16: =C11*C13 -> 3055 | D16: =D11*D13 -> 3646 | E16: =E11*E13 -> 4222
A17: Actual Revenue ($M) | B17: 2803 | C17: 3055 | D17: 3646 | E17: 4222
A19: Ads Served Growth YoY | B19: — | C19: =(C11-B11)/B11 -> 0.23560281 | D19: =(D11-C11)/C11 -> 0.29219409 | E19: =(E11-D11)/D11 -> 0.39873493
A20: Price Growth YoY | B20: — | C20: =(C13-B13)/B13 -> -0.11791745 | D20: =(D13-C13)/C13 -> -0.07641324 | E20: =(E13-D13)/D13 -> -0.17212238
A21: Volume vs Price Split
A24: Key Insight: Volume vs. Price Dynamics
A25: → Pinterest's revenue growth is driven overwhelmingly by VOLUME!!! (way more ads served)
A26: → Ad prices have declined 14% (2024) and 22% (2025); offset by 39% and 49% more ads
A27: → This "volume over price'" model creates AI risk: if engagement drops, ad volume collapses
A28: → AI disruption could reduce sessions and engagement, directly compressing ad inventory

Sheet Scenario Engine
A1: Scenario Engine: Base Case / AI Disruption / AI Integration
A3: SELECT SCENARIO: | B3: Base Case
A5: Scenario Assumptions
A6: Assumption | B6: Base Case | C6: AI Disruption | D6: AI Integration
A7: MAU Growth Rate (annual) | B7: 0.1 | C7: 0.04 | D7: 0.14
A8: US ARPU Growth Rate | B8: 0.06 | C8: -0.05 | D8: 0.12
A9: Europe ARPU Growth Rate | B9: 0.18 | C9: 0.05 | D9: 0.25
A10: ROW ARPU Growth Rate | B10: 0.35 | C10: 0.1 | D10: 0.45
A11: Engagement Change (sessions/user) | B11: 0 | C11: -0.15 | D11: 0.1
A12: Ad Load Change | B12: 0 | C12: -0.1 | D12: 0.05
A13: CPM Change | B13: 0 | C13: -0.08 | D13: 0.05
A14: Cost of Revenue Growth | B14: 0.1 | C14: 0.12 | D14: 0.15
A15: R&D Growth | B15: 0.12 | C15: 0.08 | D15: 0.2
A16: S&M Growth | B16: 0.12 | C16: 0.08 | D16: 0.15
A19: 5-Year Revenue Projection
A20: Metric | B20: 2025 (Actual) | C20: 2026E | D20: 2027E | E20: 2028E | F20: 2029E | G20: 2030E
A21: Global MAU (M) | B21: 619 | C21: =B21*(1+IF($B$3="Base Case",B7,IF($B$3="AI Disruption",C7,D7))) -> 680.9 | D21: =C21*(1+IF($B$3="Base Case",B7,IF($B$3="AI Disruption",C7,D7))) -> 748.99 | E21: =D21*(1+IF($B$3="Base Case",B7,IF($B$3="AI Disruption",C7,D7))) -> 823.889 | F21: =E21*(1+IF($B$3="Base Case",B7,IF($B$3="AI Disruption",C7,D7))) -> 906.2779 | G21: =F21*(1+IF($B$3="Base Case",B7,IF($B$3="AI Disruption",C7,D7))) -> 996.90569
A22: US & Canada MAU (M) | B22: 103 | C22: =B22*(1+IF($B$3="Base Case",B7,IF($B$3="AI Disruption",C7,D7))) -> 113.3 | D22: =C22*(1+IF($B$3="Base Case",B7,IF($B$3="AI Disruption",C7,D7))) -> 124.63 | E22: =D22*(1+IF($B$3="Base Case",B7,IF($B$3="AI Disruption",C7,D7))) -> 137.093 | F22: =E22*(1+IF($B$3="Base Case",B7,IF($B$3="AI Disruption",C7,D7))) -> 150.8023 | G22: =F22*(1+IF($B$3="Base Case",B7,IF($B$3="AI Disruption",C7,D7))) -> 165.88253
A23: Europe MAU (M) | B23: 151 | C23: =B23*(1+IF($B$3="Base Case",B7,IF($B$3="AI Disruption",C7,D7))) -> 166.1 | D23: =C23*(1+IF($B$3="Base Case",B7,IF($B$3="AI Disruption",C7,D7))) -> 182.71 | E23: =D23*(1+IF($B$3="Base Case",B7,IF($B$3="AI Disruption",C7,D7))) -> 200.981 | F23: =E23*(1+IF($B$3="Base Case",B7,IF($B$3="AI Disruption",C7,D7))) -> 221.0791 | G23: =F23*(1+IF($B$3="Base Case",B7,IF($B$3="AI Disruption",C7,D7))) -> 243.18701
A24: ROW MAU (M) | B24: 365 | C24: =B24*(1+IF($B$3="Base Case",B7,IF($B$3="AI Disruption",C7,D7))) -> 401.5 | D24: =C24*(1+IF($B$3="Base Case",B7,IF($B$3="AI Disruption",C7,D7))) -> 441.65 | E24: =D24*(1+IF($B$3="Base Case",B7,IF($B$3="AI Disruption",C7,D7))) -> 485.815 | F24: =E24*(1+IF($B$3="Base Case",B7,IF($B$3="AI Disruption",C7,D7))) -> 534.3965 | G24: =F24*(1+IF($B$3="Base Case",B7,IF($B$3="AI Disruption",C7,D7))) -> 587.83615
A25: US ARPU ($) | B25: 30.84 | C25: =B25*(1+IF($B$3="Base Case",B8,IF($B$3="AI Disruption",C8,D8))) -> 32.6904 | D25: =C25*(1+IF($B$3="Base Case",B8,IF($B$3="AI Disruption",C8,D8))) -> 34.651824 | E25: =D25*(1+IF($B$3="Base Case",B8,IF($B$3="AI Disruption",C8,D8))) -> 36.730933 | F25: =E25*(1+IF($B$3="Base Case",B8,IF($B$3="AI Disruption",C8,D8))) -> 38.934789 | G25: =F25*(1+IF($B$3="Base Case",B8,IF($B$3="AI Disruption",C8,D8))) -> 41.270877
A26: Europe ARPU ($) | B26: 5.12 | C26: =B26*(1+IF($B$3="Base Case",B9,IF($B$3="AI Disruption",C9,D9))) -> 6.0416 | D26: =C26*(1+IF($B$3="Base Case",B9,IF($B$3="AI Disruption",C9,D9))) -> 7.129088 | E26: =D26*(1+IF($B$3="Base Case",B9,IF($B$3="AI Disruption",C9,D9))) -> 8.4123238 | F26: =E26*(1+IF($B$3="Base Case",B9,IF($B$3="AI Disruption",C9,D9))) -> 9.9265421 | G26: =F26*(1+IF($B$3="Base Case",B9,IF($B$3="AI Disruption",C9,D9))) -> 11.71332
A27: ROW ARPU ($) | B27: 0.83 | C27: =B27*(1+IF($B$3="Base Case",B10,IF($B$3="AI Disruption",C10,D10))) -> 1.1205 | D27: =C27*(1+IF($B$3="Base Case",B10,IF($B$3="AI Disruption",C10,D10))) -> 1.512675 | E27: =D27*(1+IF($B$3="Base Case",B10,IF($B$3="AI Disruption",C10,D10))) -> 2.0421113 | F27: =E27*(1+IF($B$3="Base Case",B10,IF($B$3="AI Disruption",C10,D10))) -> 2.7568502 | G27: =F27*(1+IF($B$3="Base Case",B10,IF($B$3="AI Disruption",C10,D10))) -> 3.7217478
A29: US & Canada Revenue ($M) | B29: =B25*B21 -> 19089.96 | C29: =C25*C21 -> 22258.893 | D29: =D25*D21 -> 25953.87 | E29: =E25*E21 -> 30262.212 | F29: =F25*F21 -> 35285.739 | G29: =G25*G21 -> 41143.172
A30: Europe Revenue ($M) | B30: =B26*B23 -> 773.12 | C30: =C26*C23 -> 1003.5098 | D30: =D26*D23 -> 1302.5557 | E30: =E26*E23 -> 1690.7173 | F30: =F26*F23 -> 2194.551 | G30: =G26*G23 -> 2848.5272
A31: ROW Revenue ($M) | B31: =B27*B24 -> 302.95 | C31: =C27*C24 -> 449.88075 | D31: =D27*D24 -> 668.07291 | E31: =E27*E24 -> 992.08828 | F31: =F27*F24 -> 1473.2511 | G31: =G27*G24 -> 2187.7779
A32: Total Revenue ($M) | B32: =B29+B30+B31 -> 20166.03 | C32: =C29+C30+C31 -> 23712.284 | D32: =D29+D30+D31 -> 27924.498 | E32: =E29+E30+E31 -> 32945.018 | F32: =F29+F30+F31 -> 38953.541 | G32: =G29+G30+G31 -> 46179.477
A34: Cost of Revenue ($M) | B34: 842 | C34: =B34*(1+IF($B$3="Base Case",B14,IF($B$3="AI Disruption",C14,D14))) -> 926.2 | D34: =C34*(1+IF($B$3="Base Case",B14,IF($B$3="AI Disruption",C14,D14))) -> 1018.82 | E34: =D34*(1+IF($B$3="Base Case",B14,IF($B$3="AI Disruption",C14,D14))) -> 1120.702 | F34: =E34*(1+IF($B$3="Base Case",B14,IF($B$3="AI Disruption",C14,D14))) -> 1232.7722 | G34: =F34*(1+IF($B$3="Base Case",B14,IF($B$3="AI Disruption",C14,D14))) -> 1356.0494
A35: R&D ($M) | B35: 1427 | C35: =B35*(1+IF($B$3="Base Case",B15,IF($B$3="AI Disruption",C15,D15))) -> 1598.24 | D35: =C35*(1+IF($B$3="Base Case",B15,IF($B$3="AI Disruption",C15,D15))) -> 1790.0288 | E35: =D35*(1+IF($B$3="Base Case",B15,IF($B$3="AI Disruption",C15,D15))) -> 2004.8323 | F35: =E35*(1+IF($B$3="Base Case",B15,IF($B$3="AI Disruption",C15,D15))) -> 2245.4121 | G35: =F35*(1+IF($B$3="Base Case",B15,IF($B$3="AI Disruption",C15,D15))) -> 2514.8616
A36: S&M ($M) | B36: 1167 | C36: =B36*(1+IF($B$3="Base Case",B16,IF($B$3="AI Disruption",C16,D16))) -> 1307.04 | D36: =C36*(1+IF($B$3="Base Case",B16,IF($B$3="AI Disruption",C16,D16))) -> 1463.8848 | E36: =D36*(1+IF($B$3="Base Case",B16,IF($B$3="AI Disruption",C16,D16))) -> 1639.551 | F36: =E36*(1+IF($B$3="Base Case",B16,IF($B$3="AI Disruption",C16,D16))) -> 1836.2971 | G36: =F36*(1+IF($B$3="Base Case",B16,IF($B$3="AI Disruption",C16,D16))) -> 2056.6527
A37: G&A ($M) | B37: 466 | C37: =B37*(1+IF($B$3="Base Case",B14,IF($B$3="AI Disruption",C14,D14))) -> 512.6 | D37: =C37*(1+IF($B$3="Base Case",B14,IF($B$3="AI Disruption",C14,D14))) -> 563.86 | E37: =D37*(1+IF($B$3="Base Case",B14,IF($B$3="AI Disruption",C14,D14))) -> 620.246 | F37: =E37*(1+IF($B$3="Base Case",B14,IF($B$3="AI Disruption",C14,D14))) -> 682.2706 | G37: =F37*(1+IF($B$3="Base Case",B14,IF($B$3="AI Disruption",C14,D14))) -> 750.49766
A38: Total OpEx ($M) | B38: =B34+B35+B36+B37 -> 3902 | C38: =C34+C35+C36+C37 -> 4344.08 | D38: =D34+D35+D36+D37 -> 4836.5936 | E38: =E34+E35+E36+E37 -> 5385.3312 | F38: =F34+F35+F36+F37 -> 5996.752 | G38: =G34+G35+G36+G37 -> 6678.0614
A39: Operating Income ($M) | B39: =B32-B38 -> 16264.03 | C39: =C32-C38 -> 19368.204 | D39: =D32-D38 -> 23087.905 | E39: =E32-E38 -> 27559.686 | F39: =F32-F38 -> 32956.789 | G39: =G32-G38 -> 39501.416
A40: Op Margin | B40: =B39/B32 -> 0.80650629 | C40: =IF(C32=0,0,C39/C32) -> 0.81680044 | D40: =IF(D32=0,0,D39/D32) -> 0.82679748 | E40: =IF(E32=0,0,E39/E32) -> 0.83653579 | F40: =IF(F32=0,0,F39/F32) -> 0.84605374 | G40: =IF(G32=0,0,G39/G32) -> 0.85538898
A43: Scenario Comparison: 2030 Revenue Estimates
A44: Scenario | B44: 2030E Revenue ($M) | C44: vs. Base Case
A45: Base Case | B45: =103*(1.1^5)*30.84*(1.06^5) + 151*(1.1^5)*5.12*(1.18^5) + 365*(1.1^5)*0.83*(1.35^5) -> 11882.423
A46: AI Disruption | B46: =103*(1.04^5)*30.84*(0.95^5) + 151*(1.04^5)*5.12*(1.05^5) + 365*(1.04^5)*0.83*(1.1^5) -> 4784.5525 | C46: =(B46-B45)/B45 -> -0.597342
A47: AI Integration | B47: =103*(1.14^5)*30.84*(1.12^5) + 151*(1.14^5)*5.12*(1.25^5) + 365*(1.14^5)*0.83*(1.45^5) -> 19060.29 | C47: =(B47-B45)/B45 -> 0.60407445

Sheet Sensitivity Analysis
A1: Sensitivity Analysis: Revenue Impact from Key Variable Changes
A3: Panel A: US ARPU Decline Impact on Total Revenue
A4: 2025 Baseline Revenue ($M): | B4: 4222
A5: US Revenue Share of Total: | B5: =3173/4222 -> 0.75153955
A7: US ARPU Change | B7: New US ARPU ($) | C7: US Revenue Impact ($M) | D7: Total Revenue ($M) | E7: Total Revenue Change
A8: 0.05 | B8: =30.84*(1+A8) -> 32.382 | C8: =3173*A8 -> 158.65 | D8: =4222+C8 -> 4380.65 | E8: =(D8-4222)/4222 -> 0.037576978
A9: 0 | B9: =30.84*(1+A9) -> 30.84 | C9: =3173*A9 -> 0 | D9: =4222+C9 -> 4222 | E9: =(D9-4222)/4222 -> 0
A10: -0.05 | B10: =30.84*(1+A10) -> 29.298 | C10: =3173*A10 -> -158.65 | D10: =4222+C10 -> 4063.35 | E10: =(D10-4222)/4222 -> -0.037576978
A11: -0.1 | B11: =30.84*(1+A11) -> 27.756 | C11: =3173*A11 -> -317.3 | D11: =4222+C11 -> 3904.7 | E11: =(D11-4222)/4222 -> -0.075153955
A12: -0.15 | B12: =30.84*(1+A12) -> 26.214 | C12: =3173*A12 -> -475.95 | D12: =4222+C12 -> 3746.05 | E12: =(D12-4222)/4222 -> -0.11273093
A13: -0.2 | B13: =30.84*(1+A13) -> 24.672 | C13: =3173*A13 -> -634.6 | D13: =4222+C13 -> 3587.4 | E13: =(D13-4222)/4222 -> -0.15030791
A14: -0.25 | B14: =30.84*(1+A14) -> 23.13 | C14: =3173*A14 -> -793.25 | D14: =4222+C14 -> 3428.75 | E14: =(D14-4222)/4222 -> -0.18788489
A17: Panel B: Global MAU Decline Impact on Revenue
A18: MAU Change | B18: New Global MAU (M) | C18: Revenue Impact ($M) | D18: Total Revenue ($M) | E18: Total Revenue Change
A19: 0.05 | B19: =619*(1+A19) -> 649.95 | C19: =4222*A19 -> 211.1 | D19: =4222+C19 -> 4433.1 | E19: =(D19-4222)/4222 -> 0.05
A20: 0 | B20: =619*(1+A20) -> 619 | C20: =4222*A20 -> 0 | D20: =4222+C20 -> 4222 | E20: =(D20-4222)/4222 -> 0
A21: -0.05 | B21: =619*(1+A21) -> 588.05 | C21: =4222*A21 -> -211.1 | D21: =4222+C21 -> 4010.9 | E21: =(D21-4222)/4222 -> -0.05
A22: -0.1 | B22: =619*(1+A22) -> 557.1 | C22: =4222*A22 -> -422.2 | D22: =4222+C22 -> 3799.8 | E22: =(D22-4222)/4222 -> -0.1
A23: -0.15 | B23: =619*(1+A23) -> 526.15 | C23: =4222*A23 -> -633.3 | D23: =4222+C23 -> 3588.7 | E23: =(D23-4222)/4222 -> -0.15
A24: -0.2 | B24: =619*(1+A24) -> 495.2 | C24: =4222*A24 -> -844.4 | D24: =4222+C24 -> 3377.6 | E24: =(D24-4222)/4222 -> -0.2
A27: Panel C: Two Way Sensitivity: Revenue ($M) by MAU Growth × ARPU Growth
A28: MAU Growth ↓ / ARPU Growth → | B28: -0.15 | C28: -0.1 | D28: -0.05 | E28: 0 | F28: 0.05 | G28: 0.1
A29: -0.1 | B29: =(103*(1+$A29)*30.84*(1+B$28)) + (151*(1+$A29)*5.12) + (365*(1+$A29)*0.83) -> 3398.5008 | C29: =(103*(1+$A29)*30.84*(1+C$28)) + (151*(1+$A29)*5.12) + (365*(1+$A29)*0.83) -> 3541.4442 | D29: =(103*(1+$A29)*30.84*(1+D$28)) + (151*(1+$A29)*5.12) + (365*(1+$A29)*0.83) -> 3684.3876 | E29: =(103*(1+$A29)*30.84*(1+E$28)) + (151*(1+$A29)*5.12) + (365*(1+$A29)*0.83) -> 3827.331 | F29: =(103*(1+$A29)*30.84*(1+F$28)) + (151*(1+$A29)*5.12) + (365*(1+$A29)*0.83) -> 3970.2744 | G29: =(103*(1+$A29)*30.84*(1+G$28)) + (151*(1+$A29)*5.12) + (365*(1+$A29)*0.83) -> 4113.2178
A30: -0.05 | B30: =(103*(1+$A30)*30.84*(1+B$28)) + (151*(1+$A30)*5.12) + (365*(1+$A30)*0.83) -> 3587.3064 | C30: =(103*(1+$A30)*30.84*(1+C$28)) + (151*(1+$A30)*5.12) + (365*(1+$A30)*0.83) -> 3738.1911 | D30: =(103*(1+$A30)*30.84*(1+D$28)) + (151*(1+$A30)*5.12) + (365*(1+$A30)*0.83) -> 3889.0758 | E30: =(103*(1+$A30)*30.84*(1+E$28)) + (151*(1+$A30)*5.12) + (365*(1+$A30)*0.83) -> 4039.9605 | F30: =(103*(1+$A30)*30.84*(1+F$28)) + (151*(1+$A30)*5.12) + (365*(1+$A30)*0.83) -> 4190.8452 | G30: =(103*(1+$A30)*30.84*(1+G$28)) + (151*(1+$A30)*5.12) + (365*(1+$A30)*0.83) -> 4341.7299
A31: 0 | B31: =(103*(1+$A31)*30.84*(1+B$28)) + (151*(1+$A31)*5.12) + (365*(1+$A31)*0.83) -> 3776.112 | C31: =(103*(1+$A31)*30.84*(1+C$28)) + (151*(1+$A31)*5.12) + (365*(1+$A31)*0.83) -> 3934.938 | D31: =(103*(1+$A31)*30.84*(1+D$28)) + (151*(1+$A31)*5.12) + (365*(1+$A31)*0.83) -> 4093.764 | E31: =(103*(1+$A31)*30.84*(1+E$28)) + (151*(1+$A31)*5.12) + (365*(1+$A31)*0.83) -> 4252.59 | F31: =(103*(1+$A31)*30.84*(1+F$28)) + (151*(1+$A31)*5.12) + (365*(1+$A31)*0.83) -> 4411.416 | G31: =(103*(1+$A31)*30.84*(1+G$28)) + (151*(1+$A31)*5.12) + (365*(1+$A31)*0.83) -> 4570.242
A32: 0.05 | B32: =(103*(1+$A32)*30.84*(1+B$28)) + (151*(1+$A32)*5.12) + (365*(1+$A32)*0.83) -> 3964.9176 | C32: =(103*(1+$A32)*30.84*(1+C$28)) + (151*(1+$A32)*5.12) + (365*(1+$A32)*0.83) -> 4131.6849 | D32: =(103*(1+$A32)*30.84*(1+D$28)) + (151*(1+$A32)*5.12) + (365*(1+$A32)*0.83) -> 4298.4522 | E32: =(103*(1+$A32)*30.84*(1+E$28)) + (151*(1+$A32)*5.12) + (365*(1+$A32)*0.83) -> 4465.2195 | F32: =(103*(1+$A32)*30.84*(1+F$28)) + (151*(1+$A32)*5.12) + (365*(1+$A32)*0.83) -> 4631.9868 | G32: =(103*(1+$A32)*30.84*(1+G$28)) + (151*(1+$A32)*5.12) + (365*(1+$A32)*0.83) -> 4798.7541
A33: 0.1 | B33: =(103*(1+$A33)*30.84*(1+B$28)) + (151*(1+$A33)*5.12) + (365*(1+$A33)*0.83) -> 4153.7232 | C33: =(103*(1+$A33)*30.84*(1+C$28)) + (151*(1+$A33)*5.12) + (365*(1+$A33)*0.83) -> 4328.4318 | D33: =(103*(1+$A33)*30.84*(1+D$28)) + (151*(1+$A33)*5.12) + (365*(1+$A33)*0.83) -> 4503.1404 | E33: =(103*(1+$A33)*30.84*(1+E$28)) + (151*(1+$A33)*5.12) + (365*(1+$A33)*0.83) -> 4677.849 | F33: =(103*(1+$A33)*30.84*(1+F$28)) + (151*(1+$A33)*5.12) + (365*(1+$A33)*0.83) -> 4852.5576 | G33: =(103*(1+$A33)*30.84*(1+G$28)) + (151*(1+$A33)*5.12) + (365*(1+$A33)*0.83) -> 5027.2662

Sheet Geographic Opportunity
A1: Geographic Monetization Opportunity: International ARPU Convergence Model
A3: Current State: ARPU Gap Analysis (2025)
A4: Region | B4: MAU (M) | C4: ARPU ($) | D4: Revenue ($M) | E4: ARPU as % of US | F4: Monetization Gap
A5: US & Canada | B5: 103 | C5: 30.84 | D5: 3173 | E5: =C5/C5 -> 1 | F5: =1-E5 -> 0
A6: Europe | B6: 151 | C6: 5.12 | D6: 775 | E6: =C6/C5 -> 0.16601816 | F6: =1-E6 -> 0.83398184
A7: Rest of World | B7: 365 | C7: 0.83 | D7: 274 | E7: =C7/C5 -> 0.0269131 | F7: =1-E7 -> 0.9730869
A8: Global | B8: 619 | C8: 7.21 | D8: 4222 | E8: =C8/C5 -> 0.23378729 | F8: =1-E8 -> 0.76621271
A11: International ARPU Convergence Scenarios
A12: Scenario | B12: Europe Target ARPU ($) | C12: ROW Target ARPU ($) | D12: EU Rev ($M) | E12: ROW Rev ($M) | F12: Total Revenue ($M) | G12: Revenue Uplift ($M) | H12: Uplift %
A13: Current State | B13: 5.12 | C13: 0.83 | D13: =151*B13 -> 773.12 | E13: =365*C13 -> 302.95 | F13: =3173+D13+E13 -> 4249.07 | G13: =F13-F13 -> 0 | H13: =IF(F13=0,0,G13/F13) -> 0
A14: EU +50%, ROW +100% | B14: =5.12*1.5 -> 7.68 | C14: =0.83*2 -> 1.66 | D14: =151*B14 -> 1159.68 | E14: =365*C14 -> 605.9 | F14: =3173+D14+E14 -> 4938.58 | G14: =F14-F13 -> 689.51 | H14: =IF(F13=0,0,G14/F13) -> 0.16227316
A15: EU +100%, ROW +200% | B15: =5.12*2 -> 10.24 | C15: =0.83*3 -> 2.49 | D15: =151*B15 -> 1546.24 | E15: =365*C15 -> 908.85 | F15: =3173+D15+E15 -> 5628.09 | G15: =F15-F13 -> 1379.02 | H15: =IF(F13=0,0,G15/F13) -> 0.32454631
A16: EU at 50% of US, ROW at 10% | B16: =30.84*0.5 -> 15.42 | C16: =30.84*0.1 -> 3.084 | D16: =151*B16 -> 2328.42 | E16: =365*C16 -> 1125.66 | F16: =3173+D16+E16 -> 6627.08 | G16: =F16-F13 -> 2378.01 | H16: =IF(F13=0,0,G16/F13) -> 0.55965423
A17: Full Convergence to US | B17: 30.84 | C17: 30.84 | D17: =151*B17 -> 4656.84 | E17: =365*C17 -> 11256.6 | F17: =3173+D17+E17 -> 19086.44 | G17: =F17-F13 -> 14837.37 | H17: =IF(F13=0,0,G17/F13) -> 3.49191
A20: Strategic Insight
A21: → If Europe ARPU reaches 50% of US levels ($15.42), European revenue alone exceeds $2.3B which is a 3x increase.
A22: → ROW at just 10% of US ARPU ($3.08) generates $1.1B+ which is a 4x improvement over current state!!!
A23: → Full international monetization represents a ~$16B+ revenue opportunity vs. current $4.2B
A24: → AI powered personalization and shopping tools are the key enablers of international ARPU convergence

Sheet Monte Carlo Simulation
A1: Monte Carlo Risk Simulation: 1,000 Revenue Outcome Scenarios
A3: Simulation Parameters
A4: Parameter | B4: Distribution | C4: Min | D4: Max | E4: Mean | F4: Std Dev
A5: US ARPU Growth | B5: Normal | C5: -0.15 | D5: 0.15 | E5: 0.03 | F5: 0.06
A6: Europe ARPU Growth | B6: Normal | C6: -0.05 | D6: 0.35 | E6: 0.15 | F6: 0.08
A7: ROW ARPU Growth | B7: Normal | C7: 0 | D7: 0.5 | E7: 0.25 | F7: 0.1
A8: MAU Growth | B8: Normal | C8: -0.05 | D8: 0.15 | E8: 0.08 | F8: 0.04
A9: Engagement Change | B9: Normal | C9: -0.2 | D9: 0.1 | E9: -0.03 | F9: 0.07
A10: Ad Price Change | B10: Normal | C10: -0.25 | D10: 0.05 | E10: -0.1 | F10: 0.08
A13: Simulation Results (1,000 iterations)
A14: Statistic | B14: Value ($M)
A15: Mean Revenue | B15: 4705.0992
A16: Median Revenue | B16: 4700.0086
A17: Standard Deviation | B17: 441.46232
A18: Minimum | B18: 3368.3066
A19: 5th Percentile (Downside) | B19: 3976.4592
A20: 25th Percentile | B20: 4407.3027
A21: 75th Percentile | B21: 5005.968
A22: 95th Percentile (Upside) | B22: 5440.1191
A23: Maximum | B23: 6398.9594
A25: Probability Revenue < $4,000M | B25: 0.052
A26: Probability Revenue < $3,500M | B26: 0.002
A27: Probability Revenue > $5,000M | B27: 0.253
A28: Probability Revenue > $5,500M | B28: 0.039
A31: Revenue Distribution (Histogram Buckets)
A32: Revenue Bucket ($M) | B32: Count | C32: Cumulative %
A33: $2,500–$2,750 | B33: 0 | C33: 0
A34: $2,750–$3,000 | B34: 0 | C34: 0
A35: $3,000–$3,250 | B35: 0 | C35: 0
A36: $3,250–$3,500 | B36: 2 | C36: 0.002
A37: $3,500–$3,750 | B37: 12 | C37: 0.014
A38: $3,750–$4,000 | B38: 38 | C38: 0.052
A39: $4,000–$4,250 | B39: 98 | C39: 0.15
A40: $4,250–$4,500 | B40: 174 | C40: 0.324
A41: $4,500–$4,750 | B41: 228 | C41: 0.552
A42: $4,750–$5,000 | B42: 195 | C42: 0.747
A43: $5,000–$5,250 | B43: 149 | C43: 0.896
A44: $5,250–$5,500 | B44: 65 | C44: 0.961
... A50: $6,750–$7,000 | B50: 0 | C50: 1

Sheet Dashboard
A1: PINTEREST STRATEGIC ANALYSIS DASHBOARD :)
A2: How Exposed Is Pinterest to AI Disruption?
A4: FY2025 Revenue | C4: Global MAUs | F4: Adj. EBITDA | H4: Free Cash Flow | I4: Op Margin
A5: $4.22B | C5: 619M | F5: $1.27B | H5: $1.25B | I5: 7.6%
A6: +16% YoY | C6: +12% YoY | F6: +23% YoY | H6: +33% YoY | I6: +280bps YoY
A8: Revenue by Region (2025) | E8: Strategic Risk Priority Matrix
A9: Region | B9: Revenue ($M) | C9: Share | D9: ARPU ($) | E9: Risk Factor | F9: Likelihood | G9: Revenue Impact | H9: Priority
A10: US & Canada | B10: 3173 | C10: =B10/B13 -> 0.75153955 | D10: 30.84 | E10: AI search replacing discovery | F10: High | G10: High | H10: CRITICAL!!!
A11: Europe | B11: 775 | C11: =B11/B13 -> 0.18356229 | D11: 5.12 | E11: US ARPU compression | F11: Medium | G11: High | H11: HIGH
A12: Rest of World | B12: 274 | C12: =B12/B13 -> 0.064898153 | D12: 0.83 | E12: TikTok/Meta engagement shift | F12: High | G12: Medium | H12: HIGH
A13: Total | B13: 4222 | C13: 1 | D13: 7.21 | E13: International monetization lag | F13: Medium | G13: Medium | H13: MODERATE
E14: Regulatory (EU/privacy) | F14: Medium | G14: Low | H14: MODERATE
A15: Scenario Analysis: 2030 Revenue Outcomes | E15: Ad tech commoditization | F15: Low | G15: Medium | H15: LOW
A16: Scenario | B16: 2030E Revenue ($M) | C16: Implied CAGR
A17: Base Case | B17: 11882.423 | C17: 0.22992138 | E17: Strategic Options Assessment
A18: AI Disruption | B18: 4784.5525 | C18: 0.025332256 | E18: Strategy | F18: Revenue Potential | G18: Execution Risk | H18: Timeline
A19: AI Integration | B19: 19060.29 | C19: 0.35183055 | E19: AI-powered discovery engine | F19: High | G19: Medium | H19: 12-18 mo
E20: International monetization push | F20: High | G20: Medium | H20: 18-24 mo
A21: Monte Carlo Risk Assessment | E21: E-commerce / shopping ads | F21: Medium-High | G21: Low | H21: 6-12 mo
A22: Metric | B22: Value | E22: Creator economy & content | F22: Medium | G22: Medium | H22: 12-18 mo
A23: Expected Revenue (Mean) | B23: $4,705M | E23: CTV & connected advertising | F23: Medium | G23: High | H23: 18-24 mo
A24: Downside (5th %ile) | B24: $3,976M
A25: Upside (95th %ile) | B25: $5,440M
A26: P(Revenue < $4,000M) | B26: 5.2%
A27: P(Revenue > $5,000M) | B27: 25.3%
